<?xml version = '1.0' encoding = 'UTF-8'?>
<TableProxyOraclev11g class="oracle.dbtools.crest.model.design.storage.oracle.v11g.TableProxyOraclev11g" name="HISTORICO_AR" directorySegmentName="seg_0" id="1AB60A90-8181-5F81-0BF1-37EEF185ACCD">
<createdBy>paulo</createdBy>
<createdTime>2022-08-16 02:15:05 UTC</createdTime>
<ownerDesignName>TICKET_LOG</ownerDesignName>
<logging>YES</logging>
<partitionedRowMovement>DISABLE</partitionedRowMovement>
<temporaryChanged>false</temporaryChanged>
<accessDriverType>oracle_loader</accessDriverType>
<rejectLimit></rejectLimit>
<columnProxies itemClass="oracle.dbtools.crest.model.design.storage.oracle.v12c.ColumnProxyOraclev12c">
<ColumnProxy name="DT_PROXIMO_CONTATO" id="5BD805F4-BA6A-CD49-DF6E-08ADAA830852">
<createdBy>paulo</createdBy>
<createdTime>2022-08-16 02:15:05 UTC</createdTime>
<ownerDesignName>TICKET_LOG</ownerDesignName>
</ColumnProxy>
<ColumnProxy name="DT_CADASTRO" id="6824D939-3743-2591-153E-746EEE7BFB3F">
<createdBy>paulo</createdBy>
<createdTime>2022-08-16 02:15:05 UTC</createdTime>
<ownerDesignName>TICKET_LOG</ownerDesignName>
</ColumnProxy>
<ColumnProxy name="DT_MODIFICACAO" id="9B109D51-1B63-FBA5-3E09-FA0E680A403C">
<createdBy>paulo</createdBy>
<createdTime>2022-08-16 02:15:05 UTC</createdTime>
<ownerDesignName>TICKET_LOG</ownerDesignName>
</ColumnProxy>
<ColumnProxy name="CD_USUARIO" id="9C4824BF-68CF-9792-7766-647DB67F24B8">
<createdBy>paulo</createdBy>
<createdTime>2022-08-16 02:15:05 UTC</createdTime>
<ownerDesignName>TICKET_LOG</ownerDesignName>
</ColumnProxy>
<ColumnProxy name="CD_HISTORICO_CONTRATO_AR" id="A13A62E0-7913-B250-CD9C-3687E36412FE">
<createdBy>paulo</createdBy>
<createdTime>2022-08-16 02:15:05 UTC</createdTime>
<ownerDesignName>TICKET_LOG</ownerDesignName>
</ColumnProxy>
<ColumnProxy name="DT_ULTIMO_CONTATO" id="E4DE8B98-8544-F5CC-7CFF-9371CEC9995A">
<createdBy>paulo</createdBy>
<createdTime>2022-08-16 02:15:05 UTC</createdTime>
<ownerDesignName>TICKET_LOG</ownerDesignName>
</ColumnProxy>
<ColumnProxy name="CD_ESTABELECIMENTO" id="F2F42FA1-3226-918C-786A-56C2391B1194">
<createdBy>paulo</createdBy>
<createdTime>2022-08-16 02:15:05 UTC</createdTime>
<ownerDesignName>TICKET_LOG</ownerDesignName>
</ColumnProxy>
<ColumnProxy name="IND_STATUS" id="FB423ED9-F04F-1145-1987-BEC60C5CE020">
<createdBy>paulo</createdBy>
<createdTime>2022-08-16 02:15:05 UTC</createdTime>
<ownerDesignName>TICKET_LOG</ownerDesignName>
</ColumnProxy>
<ColumnProxy name="OBSERVACAO" id="FF4EDBC8-0177-AA77-66DB-D01CCEE71B5C">
<createdBy>paulo</createdBy>
<createdTime>2022-08-16 02:15:05 UTC</createdTime>
<ownerDesignName>TICKET_LOG</ownerDesignName>
</ColumnProxy>
</columnProxies>
<indexProxies>
<IndexProxy class="oracle.dbtools.crest.model.design.storage.oracle.v10g.IndexProxyOraclev10g" name="IX_Relationship35" id="818D879B-1A55-CB80-2C9C-BBA997EC49DC">
<createdBy>paulo</createdBy>
<createdTime>2022-08-16 02:15:05 UTC</createdTime>
<ownerDesignName>TICKET_LOG</ownerDesignName>
<nameHasQuotes>true</nameHasQuotes>
<logging></logging>
</IndexProxy>
<IndexProxy class="oracle.dbtools.crest.model.design.storage.oracle.v10g.IndexProxyOraclev10g" name="IX_Relationship34" id="DD193561-9E37-E75D-E483-B3A87F48185A">
<createdBy>paulo</createdBy>
<createdTime>2022-08-16 02:15:05 UTC</createdTime>
<ownerDesignName>TICKET_LOG</ownerDesignName>
<nameHasQuotes>true</nameHasQuotes>
<logging></logging>
</IndexProxy>
</indexProxies>
<foreignKeys>
<ForeignKey class="oracle.dbtools.crest.model.design.storage.oracle.v10g.FKProxyOraclev10g" name="Relationship35" id="72A4E072-03F6-7427-BE12-D8A54952E514">
<createdBy>paulo</createdBy>
<createdTime>2022-08-16 02:15:05 UTC</createdTime>
<ownerDesignName>TICKET_LOG</ownerDesignName>
<nameHasQuotes>true</nameHasQuotes>
</ForeignKey>
<ForeignKey class="oracle.dbtools.crest.model.design.storage.oracle.v10g.FKProxyOraclev10g" name="Relationship34" id="8D1F22D0-7034-E607-C1C5-51A7960232CB">
<createdBy>paulo</createdBy>
<createdTime>2022-08-16 02:15:05 UTC</createdTime>
<ownerDesignName>TICKET_LOG</ownerDesignName>
<nameHasQuotes>true</nameHasQuotes>
</ForeignKey>
</foreignKeys>
<primaryKeys>
<PrimaryKey class="oracle.dbtools.crest.model.design.storage.oracle.v10g.PKProxyOraclev10g" name="PK_HISTORICO_AR" id="D47A6EDD-64E9-165D-C555-A079ABDF203A">
<createdBy>paulo</createdBy>
<createdTime>2022-08-16 02:15:05 UTC</createdTime>
<ownerDesignName>TICKET_LOG</ownerDesignName>
<indexSort>SORTED</indexSort>
</PrimaryKey>
</primaryKeys>
</TableProxyOraclev11g>